{
  "version": "7",
  "dialect": "mysql",
  "entries": [
    {
      "idx": 0,
      "version": "5",
      "when": 1774759688538,
      "tag": "0000_careful_the_hood",
      "breakpoints": true
    },
    {
      "idx": 1,
      "version": "5",
      "when": 1774759733722,
      "tag": "0001_nervous_invaders",
      "breakpoints": true
    },
    {
      "idx": 2,
      "version": "5",
      "when": 1774760760966,
      "tag": "0002_steady_sauron",
      "breakpoints": true
    },
    {
      "idx": 3,
      "version": "5",
      "when": 1774760902624,
      "tag": "0003_dusty_randall_flagg",
      "breakpoints": true
    },
    {
      "idx": 4,
      "version": "5",
      "when": 1774761451524,
      "tag": "0004_unusual_molten_man",
      "breakpoints": true
    },
    {
      "idx": 5,
      "version": "5",
      "when": 1774767120751,
      "tag": "0005_abnormal_warlock",
      "breakpoints": true
    }
  ]
}